tqu/__init__.py
tqu/__main__.py
tqu/cli.py
tqu/db.py
tqu/exceptions.py
tqu-1.0.2.dist-info/METADATA
tqu-1.0.2.dist-info/WHEEL
tqu-1.0.2.dist-info/entry_points.txt
tqu-1.0.2.dist-info/licenses/LICENSE
tqu-1.0.2.dist-info/RECORD
