Metadata-Version: 2.4
Name: tqu
Version: 1.0.2
Summary: A Minimal CLI for Queue-Based Task Tracking
Project-URL: Homepage, https://github.com/primaprashant/tqu
Project-URL: Issues, https://github.com/primaprashant/tqu/issues
License-Expression: MIT
License-File: LICENSE
Classifier: Operating System :: OS Independent
Classifier: Programming Language :: Python :: 3
Requires-Python: >=3.9
Requires-Dist: click>=8.1.8
Requires-Dist: rich>=13.9.4
